iOSDefaults/__init__.py
iOSDefaults/cli.py
iosdefaults-1.2.0.dist-info/LICENSE
iosdefaults-1.2.0.dist-info/METADATA
iosdefaults-1.2.0.dist-info/WHEEL
iosdefaults-1.2.0.dist-info/entry_points.txt
iosdefaults-1.2.0.dist-info/top_level.txt
iosdefaults-1.2.0.dist-info/RECORD
