Metadata-Version: 2.2
Name: iosdefaults
Version: 1.2.0
Summary: Command line tool for editing app user-preferences on iOS devices through usb
Home-page: https://github.com/Maxmad68/iOSDefaults
Author: Maxime MADRAU
Author-email: maxime@madrau.fr
License: GPL-3.0-or-later
Classifier: Programming Language :: Python :: 3
Classifier: License :: OSI Approved :: GNU General Public License v3 (GPLv3)
Classifier: Operating System :: OS Independent
Requires-Python: >=3.6
License-File: LICENSE
Requires-Dist: pymobiledevice3
Dynamic: author
Dynamic: author-email
Dynamic: classifier
Dynamic: description
Dynamic: description-content-type
Dynamic: home-page
Dynamic: license
Dynamic: requires-dist
Dynamic: requires-python
Dynamic: summary
